name4py/__init__.py
name4py/name_generator.py
name4py/enum/__init__.py
name4py/enum/country.py
name4py/enum/gender.py
name4py/resource/__init__.py
name4py-0.1.4.dist-info/licenses/LICENSE
name4py-0.1.4.dist-info/METADATA
name4py-0.1.4.dist-info/WHEEL
name4py-0.1.4.dist-info/top_level.txt
name4py-0.1.4.dist-info/RECORD
