Metadata-Version: 2.4
Name: name4py
Version: 0.1.4
Summary: Generate names in every language.
Requires-Python: >=3.10
License-File: LICENSE
Requires-Dist: gdown
Requires-Dist: vortezwohl>=0.0.8
Dynamic: license-file
